itunesmusicsearch/__init__.py
itunesmusicsearch/result_item.py
itunesmusicsearch/track.py
itunesmusicsearch-0.0.1.dist-info/METADATA
itunesmusicsearch-0.0.1.dist-info/RECORD
itunesmusicsearch-0.0.1.dist-info/WHEEL
itunesmusicsearch-0.0.1.dist-info/top_level.txt
