Metadata-Version: 2.1
Name: itunesmusicsearch
Version: 0.0.1
Summary: A small iTunes API wrapper (made for test task)
Home-page: https://github.com/fonrims/itunesmusicsearch
Author: Andrii Smirnov
Author-email: andrew.fonrims@gmail.com
License: MIT
Platform: UNKNOWN
Classifier: Programming Language :: Python :: 3
Classifier: Programming Language :: Python :: 3.4
Classifier: Programming Language :: Python :: 3.5
Classifier: Programming Language :: Python :: 3.6
Classifier: Intended Audience :: Developers
Classifier: Topic :: Software Development :: Libraries :: Python Modules
Classifier: License :: OSI Approved :: MIT License
Classifier: Operating System :: OS Independent
Requires-Dist: requests (>=2.8)
